AUTHORS.rst
CONTRIBUTING.rst
HISTORY.rst
LICENSE
MANIFEST.in
README.rst
setup.cfg
setup.py
docs/Makefile
docs/authors.rst
docs/conf.py
docs/contributing.rst
docs/history.rst
docs/index.rst
docs/installation.rst
docs/make.bat
docs/readme.rst
docs/usage.rst
tc2calculator/cli.py
tc2calculator/tc2calculator.py
tc2calculator.egg-info/PKG-INFO
tc2calculator.egg-info/SOURCES.txt
tc2calculator.egg-info/dependency_links.txt
tc2calculator.egg-info/entry_points.txt
tc2calculator.egg-info/not-zip-safe
tc2calculator.egg-info/requires.txt
tc2calculator.egg-info/top_level.txt
tests/__init__.py
tests/test_tc2calculator.py