Metadata-Version: 1.2
Name: tc2calculator
Version: 1.2
Summary: Adds and subtracts 2 number - demo project
Home-page: https://github.com/marklaszlo9/tc2calculator
Author: Mark Laszlo
Author-email: mark.laszlo@tc2.hu
License: MIT license
Keywords: tc2calculator
Platform: UNKNOWN
Classifier: Development Status :: 2 - Pre-Alpha
Classifier: Intended Audience :: Developers
Classifier: License :: OSI Approved :: MIT License
Classifier: Natural Language :: English
Classifier: Programming Language :: Python :: 3
Classifier: Programming Language :: Python :: 3.5
Classifier: Programming Language :: Python :: 3.6
Classifier: Programming Language :: Python :: 3.7
Classifier: Programming Language :: Python :: 3.8
Requires-Python: >=3.5
